Metadata-Version: 2.3
Name: donnes-des-sous-hakim
Version: 0.1.1
Summary: Add your description here
Author: Hakim
Author-email: Hakim <hakimfidjel.pro@gmail.com>
Requires-Dist: httpx>=0.28.1
Requires-Python: >=3.12
